LICENSE
MANIFEST.in
pavement.py
paver-minilib.zip
ptracemodule.c
setup.py
ptrace.egg-info/PKG-INFO
ptrace.egg-info/SOURCES.txt
ptrace.egg-info/dependency_links.txt
ptrace.egg-info/top_level.txt