Metadata-Version: 1.0
Name: ptrace
Version: 1.0
Summary: C extension providing access to ptrace(2)
Home-page: UNKNOWN
Author: Libor Michalek
Author-email: libor@pobox.com
License: bsd
Platform: UNKNOWN
Classifier: Development Status :: 5 - Production/Stable
Classifier: Intended Audience :: Developers
Classifier: License :: OSI Approved :: BSD License
Classifier: Natural Language :: English
Classifier: Operating System :: Unix
Classifier: Programming Language :: C
Classifier: Topic :: System :: Networking
